sqlphile/__init__.py
sqlphile/d.py
sqlphile/db3.py
sqlphile/dbtypes.py
sqlphile/django.py
sqlphile/f.py
sqlphile/model.py
sqlphile/my1.py
sqlphile/ora.py
sqlphile/pg2.py
sqlphile/q.py
sqlphile/skitai_compat.py
sqlphile/sql.py
sqlphile/sqlmap.py
sqlphile/utils.py
sqlphile-0.9.7.dist-info/LICENSE
sqlphile-0.9.7.dist-info/METADATA
sqlphile-0.9.7.dist-info/WHEEL
sqlphile-0.9.7.dist-info/top_level.txt
sqlphile-0.9.7.dist-info/RECORD
