Metadata-Version: 2.1
Name: sqlphile
Version: 0.9.7
Summary: SQL Phile
Home-page: https://gitlab.com/skitai/sqlphile
Author: Hans Roh
Author-email: hansroh@gmail.com
License: MIT
Download-URL: https://pypi.python.org/pypi/sqlphile
Platform: posix
Platform: nt
Classifier: License :: OSI Approved :: MIT License
Classifier: Development Status :: 4 - Beta
Classifier: Topic :: Database
Classifier: Intended Audience :: Developers
Classifier: Programming Language :: Python
Classifier: Programming Language :: Python :: 3
License-File: LICENSE
Requires-Dist: rs4 (>=0.3)
